autodistill_yolonas/__init__.py
autodistill_yolonas/yolonas_model.py
autodistill_yolonas-0.1.1.dist-info/LICENSE
autodistill_yolonas-0.1.1.dist-info/METADATA
autodistill_yolonas-0.1.1.dist-info/WHEEL
autodistill_yolonas-0.1.1.dist-info/top_level.txt
autodistill_yolonas-0.1.1.dist-info/RECORD
